{
	"$schema": "https://schemas.wp.org/trunk/block.json",
	"apiVersion": 2,
	"name": "novablocks/supernova",
	"title": "Supernova",
	"category": "nova-blocks",
	"description": "Create amazing layouts from your posts or static content.",
	"keywords": ["posts", "grid", "layout", "query", "parametric"],
	"textdomain": "nova-blocks",
	"attributes": {},
	"usesContext": [
		"queryId",
		"query",
		"queryContext",
		"templateSlug"
	],
	"providesContext": {
		"queryId": "queryId",
		"query": "query"
	},
	"supports": {
		"html": false,
		"novaBlocks": {
			"colorSignal": {
				"attributes": true,
				"controls": true
			},
			"spaceAndSizing": {
				"attributes": true,
				"controls": true,
				"advancedSpacing": true
			},
			"customAlign": true,
			"contentPosition": {
				"attributes": true,
				"controls": true
			},
			"collectionContent": {
				"attributes": true,
				"controls": true
			},
			"collectionLayout": {
				"attributes": true,
				"controls": true
			},
			"cardElementsVisibility": {
				"attributes": true,
				"controls": true
			},
			"cardElementsStacking": {
				"attributes": true,
				"controls": true
			},

			"mediaComposition": {
				"attributes": true,
				"controls": true
			},
			"overlayFilter": {
				"attributes": true,
				"controls": true,
				"duotone": ".blob-mix__media"
			},
			"scrollingEffect": {
				"attributes": true,
				"controls": true,
				"customWrapper": true,
				"doppler": true
			},
			"shapeModeling": {
				"attributes": true,
				"controls": true
			}
		},
		"color": {
			"text": false,
			"background": false
		}
	}
}
