{
	"align": {
		"type": "string",
		"default": "full"
	},
	"mediaPosition": {
		"type": "string",
		"default": "left"
	},
	"blockStyle": {
		"type": "string",
		"default": "basic"
	},
	"contentStyle": {
		"type": "string",
		"default": "basic"
	},
	"horizontalAlignment": {
		"type": "string",
		"default": "center"
	},
	"verticalAlignment": {
		"type": "string",
		"default": ""
	},
	"emphasisArea": {
		"type": "number",
		"default": 100
	},
	"contentAreaWidth": {
		"type": "number",
		"default": 50
	},
	"balanceEmphasis": {
		"type": "number",
		"default": 0
	},
	"balanceFocalPoint": {
		"type": "string",
		"default": "content"
	},
	"layoutPreset": {
		"type": "string",
		"default": "stable"
	},
	"upgradedToModerate": {
		"type": "boolean",
		"default": false
	}
}
